plivo.py
plivoxml.py
setup.py
plivo_six.egg-info/PKG-INFO
plivo_six.egg-info/SOURCES.txt
plivo_six.egg-info/dependency_links.txt
plivo_six.egg-info/requires.txt
plivo_six.egg-info/top_level.txt