Metadata-Version: 1.1
Name: plivo-six
Version: 0.11.5
Summary: Plivo Python library
Home-page: https://github.com/phuong/plivo-python
Author: Plivo Team
Author-email: hello@plivo.com
License: UNKNOWN
Keywords: plivo,rest
Platform: UNKNOWN
Classifier: Programming Language :: Python
Classifier: Operating System :: OS Independent
Classifier: License :: OSI Approved :: MIT License
Classifier: Intended Audience :: Developers
Classifier: Development Status :: 5 - Production/Stable
Classifier: Topic :: Software Development :: Libraries :: Python Modules
Classifier: Topic :: Communications :: Telephony
